src/alu.v
module Alu #(parameter OPERAND_SIZE=32)(
    input [1:0] function_block,
    input [2:0] operation,
    input [OPERAND_SIZE-1:0] operand1,
    input [OPERAND_SIZE-1:0] operand2,
    output [OPERAND_SIZE-1:0] result,
    output zero);

    assign result = operand1 + operand2;

    assign zero = (result == 0);

endmodule

src/register_bank.v
module Register_bank #(parameter REGISTER_SIZE=32, ADDRESS_SIZE=5)(
    input clk,
    input reset,
    input [REGISTER_SIZE-1:0] data_in,
    output [REGISTER_SIZE-1:0] data_out1,
    output [REGISTER_SIZE-1:0] data_out2,
    input write,
    input [ADDRESS_SIZE-1:0] addr_out1,
    input [ADDRESS_SIZE-1:0] addr_out2,
    input [ADDRESS_SIZE-1:0] addr_in);

    reg [REGISTER_SIZE-1:0] bank [(1<<ADDRESS_SIZE)-1:0];

    always @(posedge clk)
    begin

        if(write && (addr_in != 5'b0)) 
        begin
            bank[addr_in] = data_in;
        end
    end

    integer i;
    always @(posedge reset)
    begin
        for (i=0; i<(1<<ADDRESS_SIZE); i=i+1) bank[i] <= 32'h0;
    end

    assign data_out1 = bank[addr_out1];
    assign data_out2 = bank[addr_out2];

endmodule

src/decoder.v
module Decoder #(parameter ADDRESS_SIZE=32, REG_ADDRESS_SIZE=5)(
    input [ADDRESS_SIZE-1:0] instruction,
    
    output [REG_ADDRESS_SIZE-1:0] addr_r1,
    output [REG_ADDRESS_SIZE-1:0] addr_r2,
    
    output [REG_ADDRESS_SIZE-1:0] addr_rd,
    output register_write,
    
    output [ADDRESS_SIZE-1:0] immediate,
    output use_immediate,
    
    output [1:0] function_block,
    output [2:0] operation);

    assign addr_r1 = instruction[19:15];
    assign addr_r2 = 5'h0;
    assign addr_rd = instruction[11:7];
    assign immediate[ADDRESS_SIZE-1:0] = { {20{instruction[31]}} , instruction[31:20] };
    
    assign register_write = 1'b1;
    assign use_immediate = 1;

    assign function_block = 2'b0;
    assign operation = instruction[14:12];

endmodule

src/imem.v
module Imem #(parameter ADDRESS_SIZE=32, BOOT_ADDRESS=32'h1000, MEM_SIZE=32'h1000)(
    input reset,
    input [ADDRESS_SIZE-1:0] address,
    output [ADDRESS_SIZE-1:0] instruction);

    reg [7:0] memory [BOOT_ADDRESS+MEM_SIZE:BOOT_ADDRESS];

    initial $readmemb("mem/imem.dat", memory); 

    assign instruction = 
        (address >= BOOT_ADDRESS  && address <= BOOT_ADDRESS + MEM_SIZE - 4)? { memory[address], memory[address+1], memory[address+2], memory[address+3]}
        : 32'h0;


endmodule

src/datapath.v
module Datapath #(parameter ADDRESS_SIZE=32, BOOT_ADDRESS=32'h1000, MEM_SIZE=32'h1000, REG_ADDRESS_SIZE=5)(
    input reset,
    input clk);

    reg [ADDRESS_SIZE-1:0] pc;

    wire [ADDRESS_SIZE-1:0] instruction;

    wire [REG_ADDRESS_SIZE-1:0] addr_r1;
    wire [REG_ADDRESS_SIZE-1:0] addr_r2;
    wire [REG_ADDRESS_SIZE-1:0] addr_rd;
    wire [ADDRESS_SIZE-1:0] immediate;
    wire register_write;
    wire use_immediate;
    wire [1:0] function_block;
    wire [2:0] operation;

    wire [ADDRESS_SIZE-1:0] data_r1;
    wire [ADDRESS_SIZE-1:0] data_r2;
    wire [ADDRESS_SIZE-1:0] result;

    wire zero;
    wire [ADDRESS_SIZE-1:0] operand2;


    initial pc <= BOOT_ADDRESS;

    always @(posedge clk) begin
        pc = pc+4;
    end

    assign operand2 =
        (use_immediate)? immediate
        : data_r2;

    Imem #(
        .BOOT_ADDRESS(BOOT_ADDRESS)
    ) imem(
        .reset(reset),
        .address(pc),
        .instruction(instruction));

    Decoder decoder(
        .instruction(instruction),
        .addr_r1(addr_r1),
        .addr_r2(addr_r2),
        .addr_rd(addr_rd),
        .register_write(register_write),
        .immediate(immediate),
        .use_immediate(use_immediate),
        .function_block(function_block),
        .operation(operation));

    Register_bank rbank(
        .clk(clk),
        .reset(reset),
        .addr_in(addr_rd),
        .data_in(result),
        .write(register_write),
        .addr_out1(addr_r1),
        .data_out1(data_r1),
        .addr_out2(addr_r2),
        .data_out2(data_r2));

    Alu alu(
        .function_block(function_block),
        .operation(operation),
        .operand1(data_r1),
        .operand2(operand2),
        .result(result),
        .zero(zero));


endmodule

tests/test_datapath.v
module test;

    reg reset = 1;
    reg clk = 0;

    initial begin
        $dumpfile("test.vcd");
        $dumpvars(0, test);

        #1 reset = 0;

        #400 $finish;
    end

    always #1 clk = !clk;

    Datapath dpath(
        .reset(reset),
        .clk(clk));

endmodule // test

graphs/datapath.vcd
$date
	Sat Dec 16 15:28:11 2017
$end
$version
	Icarus Verilog
$end
$timescale
	1s
$end
$scope module test $end
$var reg 1 ! clk $end
$var reg 1 " reset $end
$scope module dpath $end
$var wire 5 # addr_r2 [4:0] $end
$var wire 1 ! clk $end
$var wire 2 $ function_block [1:0] $end
$var wire 32 % operand2 [31:0] $end
$var wire 1 & register_write $end
$var wire 1 " reset $end
$var wire 1 ' use_immediate $end
$var wire 1 ( zero $end
$var wire 32 ) result [31:0] $end
$var wire 3 * operation [2:0] $end
$var wire 32 + instruction [31:0] $end
$var wire 32 , immediate [31:0] $end
$var wire 32 - data_r2 [31:0] $end
$var wire 32 . data_r1 [31:0] $end
$var wire 5 / addr_rd [4:0] $end
$var wire 5 0 addr_r1 [4:0] $end
$var reg 32 1 pc [31:0] $end
$scope module alu $end
$var wire 2 2 function_block [1:0] $end
$var wire 32 3 operand2 [31:0] $end
$var wire 1 ( zero $end
$var wire 32 4 result [31:0] $end
$var wire 3 5 operation [2:0] $end
$var wire 32 6 operand1 [31:0] $end
$upscope $end
$scope module decoder $end
$var wire 5 7 addr_r2 [4:0] $end
$var wire 2 8 function_block [1:0] $end
$var wire 1 & register_write $end
$var wire 1 ' use_immediate $end
$var wire 3 9 operation [2:0] $end
$var wire 32 : instruction [31:0] $end
$var wire 32 ; immediate [31:0] $end
$var wire 5 < addr_rd [4:0] $end
$var wire 5 = addr_r1 [4:0] $end
$upscope $end
$scope module imem $end
$var wire 32 > address [31:0] $end
$var wire 1 " reset $end
$var wire 32 ? instruction [31:0] $end
$upscope $end
$scope module rbank $end
$var wire 5 @ addr_in [4:0] $end
$var wire 5 A addr_out1 [4:0] $end
$var wire 5 B addr_out2 [4:0] $end
$var wire 1 ! clk $end
$var wire 32 C data_in [31:0] $end
$var wire 32 D data_out1 [31:0] $end
$var wire 32 E data_out2 [31:0] $end
$var wire 1 " reset $end
$var wire 1 & write $end
$var integer 32 F i [31:0] $end
$upscope $end
$upscope $end
$upscope $end
$enddefinitions $end
#0
$dumpvars
b100000 F
b0 E
b0 D
b1 C
b0 B
b0 A
b1 @
b100000000000010010011 ?
b1000000000000 >
b0 =
b1 <
b1 ;
b100000000000010010011 :
b0 9
b0 8
b0 7
b0 6
b0 5
b1 4
b1 3
b0 2
b1000000000000 1
b0 0
b1 /
b0 .
b0 -
b1 ,
b100000000000010010011 +
b0 *
b1 )
0(
1'
1&
b1 %
b0 $
b0 #
1"
0!
$end
#1
b10 )
b10 4
b10 C
b1 .
b1 6
b1 D
b1 0
b1 =
b1 A
b100001000000010010011 +
b100001000000010010011 :
b100001000000010010011 ?
b1000000000100 1
b1000000000100 >
1!
0"
#2
0!
#3
b1000000001000 1
b1000000001000 >
b11 )
b11 4
b11 C
b10 .
b10 6
b10 D
1!
#4
0!
#5
b100 )
b100 4
b100 C
b11 .
b11 6
b11 D
b1000000001100 1
b1000000001100 >
1!
#6
0!
#7
b1000000010000 1
b1000000010000 >
b101 )
b101 4
b101 C
b100 .
b100 6
b100 D
1!
#8
0!
#9
b110 )
b110 4
b110 C
b101 .
b101 6
b101 D
b1000000010100 1
b1000000010100 >
1!
#10
0!
#11
b1000000011000 1
b1000000011000 >
b111 )
b111 4
b111 C
b110 .
b110 6
b110 D
1!
#12
0!
#13
b1000 )
b1000 4
b1000 C
b111 .
b111 6
b111 D
b1000000011100 1
b1000000011100 >
1!
#14
0!
#15
b1000000100000 1
b1000000100000 >
b1001 )
b1001 4
b1001 C
b1000 .
b1000 6
b1000 D
1!
#16
0!
#17
b1010 )
b1010 4
b1010 C
b1001 .
b1001 6
b1001 D
b1000000100100 1
b1000000100100 >
1!
#18
0!
#19
b1000000101000 1
b1000000101000 >
b1011 )
b1011 4
b1011 C
b1010 .
b1010 6
b1010 D
1!
#20
0!
#21
b1100 )
b1100 4
b1100 C
b1011 .
b1011 6
b1011 D
b1000000101100 1
b1000000101100 >
1!
#22
0!
#23
b1000000110000 1
b1000000110000 >
b1101 )
b1101 4
b1101 C
b1100 .
b1100 6
b1100 D
1!
#24
0!
#25
b1110 )
b1110 4
b1110 C
b1101 .
b1101 6
b1101 D
b1000000110100 1
b1000000110100 >
1!
#26
0!
#27
b1000000111000 1
b1000000111000 >
b1111 )
b1111 4
b1111 C
b1110 .
b1110 6
b1110 D
1!
#28
0!
#29
1(
b0 %
b0 3
b0 ,
b0 ;
b0 /
b0 <
b0 @
b0 0
b0 =
b0 A
b0 +
b0 :
b0 ?
b0 )
b0 4
b0 C
b0 .
b0 6
b0 D
b1000000111100 1
b1000000111100 >
1!
#30
0!
#31
b1000001000000 1
b1000001000000 >
1!
#32
0!
#33
b1000001000100 1
b1000001000100 >
1!
#34
0!
#35
b1000001001000 1
b1000001001000 >
1!
#36
0!
#37
b1000001001100 1
b1000001001100 >
1!
#38
0!
#39
b1000001010000 1
b1000001010000 >
1!
#40
0!
#41
b1000001010100 1
b1000001010100 >
1!
#42
0!
#43
b1000001011000 1
b1000001011000 >
1!
#44
0!
#45
b1000001011100 1
b1000001011100 >
1!
#46
0!
#47
b1000001100000 1
b1000001100000 >
1!
#48
0!
#49
b1000001100100 1
b1000001100100 >
1!
#50
0!
#51
b1000001101000 1
b1000001101000 >
1!
#52
0!
#53
b1000001101100 1
b1000001101100 >
1!
#54
0!
#55
b1000001110000 1
b1000001110000 >
1!
#56
0!
#57
b1000001110100 1
b1000001110100 >
1!
#58
0!
#59
b1000001111000 1
b1000001111000 >
1!
#60
0!
#61
b1000001111100 1
b1000001111100 >
1!
#62
0!
#63
b1000010000000 1
b1000010000000 >
1!
#64
0!
#65
b1000010000100 1
b1000010000100 >
1!
#66
0!
#67
b1000010001000 1
b1000010001000 >
1!
#68
0!
#69
b1000010001100 1
b1000010001100 >
1!
#70
0!
#71
b1000010010000 1
b1000010010000 >
1!
#72
0!
#73
b1000010010100 1
b1000010010100 >
1!
#74
0!
#75
b1000010011000 1
b1000010011000 >
1!
#76
0!
#77
b1000010011100 1
b1000010011100 >
1!
#78
0!
#79
b1000010100000 1
b1000010100000 >
1!
#80
0!
#81
b1000010100100 1
b1000010100100 >
1!
#82
0!
#83
b1000010101000 1
b1000010101000 >
1!
#84
0!
#85
b1000010101100 1
b1000010101100 >
1!
#86
0!
#87
b1000010110000 1
b1000010110000 >
1!
#88
0!
#89
b1000010110100 1
b1000010110100 >
1!
#90
0!
#91
b1000010111000 1
b1000010111000 >
1!
#92
0!
#93
b1000010111100 1
b1000010111100 >
1!
#94
0!
#95
b1000011000000 1
b1000011000000 >
1!
#96
0!
#97
b1000011000100 1
b1000011000100 >
1!
#98
0!
#99
b1000011001000 1
b1000011001000 >
1!
#100
0!
#101
b1000011001100 1
b1000011001100 >
1!
#102
0!
#103
b1000011010000 1
b1000011010000 >
1!
#104
0!
#105
b1000011010100 1
b1000011010100 >
1!
#106
0!
#107
b1000011011000 1
b1000011011000 >
1!
#108
0!
#109
b1000011011100 1
b1000011011100 >
1!
#110
0!
#111
b1000011100000 1
b1000011100000 >
1!
#112
0!
#113
b1000011100100 1
b1000011100100 >
1!
#114
0!
#115
b1000011101000 1
b1000011101000 >
1!
#116
0!
#117
b1000011101100 1
b1000011101100 >
1!
#118
0!
#119
b1000011110000 1
b1000011110000 >
1!
#120
0!
#121
b1000011110100 1
b1000011110100 >
1!
#122
0!
#123
b1000011111000 1
b1000011111000 >
1!
#124
0!
#125
b1000011111100 1
b1000011111100 >
1!
#126
0!
#127
b1000100000000 1
b1000100000000 >
1!
#128
0!
#129
b1000100000100 1
b1000100000100 >
1!
#130
0!
#131
b1000100001000 1
b1000100001000 >
1!
#132
0!
#133
b1000100001100 1
b1000100001100 >
1!
#134
0!
#135
b1000100010000 1
b1000100010000 >
1!
#136
0!
#137
b1000100010100 1
b1000100010100 >
1!
#138
0!
#139
b1000100011000 1
b1000100011000 >
1!
#140
0!
#141
b1000100011100 1
b1000100011100 >
1!
#142
0!
#143
b1000100100000 1
b1000100100000 >
1!
#144
0!
#145
b1000100100100 1
b1000100100100 >
1!
#146
0!
#147
b1000100101000 1
b1000100101000 >
1!
#148
0!
#149
b1000100101100 1
b1000100101100 >
1!
#150
0!
#151
b1000100110000 1
b1000100110000 >
1!
#152
0!
#153
b1000100110100 1
b1000100110100 >
1!
#154
0!
#155
b1000100111000 1
b1000100111000 >
1!
#156
0!
#157
b1000100111100 1
b1000100111100 >
1!
#158
0!
#159
b1000101000000 1
b1000101000000 >
1!
#160
0!
#161
b1000101000100 1
b1000101000100 >
1!
#162
0!
#163
b1000101001000 1
b1000101001000 >
1!
#164
0!
#165
b1000101001100 1
b1000101001100 >
1!
#166
0!
#167
b1000101010000 1
b1000101010000 >
1!
#168
0!
#169
b1000101010100 1
b1000101010100 >
1!
#170
0!
#171
b1000101011000 1
b1000101011000 >
1!
#172
0!
#173
b1000101011100 1
b1000101011100 >
1!
#174
0!
#175
b1000101100000 1
b1000101100000 >
1!
#176
0!
#177
b1000101100100 1
b1000101100100 >
1!
#178
0!
#179
b1000101101000 1
b1000101101000 >
1!
#180
0!
#181
b1000101101100 1
b1000101101100 >
1!
#182
0!
#183
b1000101110000 1
b1000101110000 >
1!
#184
0!
#185
b1000101110100 1
b1000101110100 >
1!
#186
0!
#187
b1000101111000 1
b1000101111000 >
1!
#188
0!
#189
b1000101111100 1
b1000101111100 >
1!
#190
0!
#191
b1000110000000 1
b1000110000000 >
1!
#192
0!
#193
b1000110000100 1
b1000110000100 >
1!
#194
0!
#195
b1000110001000 1
b1000110001000 >
1!
#196
0!
#197
b1000110001100 1
b1000110001100 >
1!
#198
0!
#199
b1000110010000 1
b1000110010000 >
1!
#200
0!
#201
b1000110010100 1
b1000110010100 >
1!
#202
0!
#203
b1000110011000 1
b1000110011000 >
1!
#204
0!
#205
b1000110011100 1
b1000110011100 >
1!
#206
0!
#207
b1000110100000 1
b1000110100000 >
1!
#208
0!
#209
b1000110100100 1
b1000110100100 >
1!
#210
0!
#211
b1000110101000 1
b1000110101000 >
1!
#212
0!
#213
b1000110101100 1
b1000110101100 >
1!
#214
0!
#215
b1000110110000 1
b1000110110000 >
1!
#216
0!
#217
b1000110110100 1
b1000110110100 >
1!
#218
0!
#219
b1000110111000 1
b1000110111000 >
1!
#220
0!
#221
b1000110111100 1
b1000110111100 >
1!
#222
0!
#223
b1000111000000 1
b1000111000000 >
1!
#224
0!
#225
b1000111000100 1
b1000111000100 >
1!
#226
0!
#227
b1000111001000 1
b1000111001000 >
1!
#228
0!
#229
b1000111001100 1
b1000111001100 >
1!
#230
0!
#231
b1000111010000 1
b1000111010000 >
1!
#232
0!
#233
b1000111010100 1
b1000111010100 >
1!
#234
0!
#235
b1000111011000 1
b1000111011000 >
1!
#236
0!
#237
b1000111011100 1
b1000111011100 >
1!
#238
0!
#239
b1000111100000 1
b1000111100000 >
1!
#240
0!
#241
b1000111100100 1
b1000111100100 >
1!
#242
0!
#243
b1000111101000 1
b1000111101000 >
1!
#244
0!
#245
b1000111101100 1
b1000111101100 >
1!
#246
0!
#247
b1000111110000 1
b1000111110000 >
1!
#248
0!
#249
b1000111110100 1
b1000111110100 >
1!
#250
0!
#251
b1000111111000 1
b1000111111000 >
1!
#252
0!
#253
b1000111111100 1
b1000111111100 >
1!
#254
0!
#255
b1001000000000 1
b1001000000000 >
1!
#256
0!
#257
b1001000000100 1
b1001000000100 >
1!
#258
0!
#259
b1001000001000 1
b1001000001000 >
1!
#260
0!
#261
b1001000001100 1
b1001000001100 >
1!
#262
0!
#263
b1001000010000 1
b1001000010000 >
1!
#264
0!
#265
b1001000010100 1
b1001000010100 >
1!
#266
0!
#267
b1001000011000 1
b1001000011000 >
1!
#268
0!
#269
b1001000011100 1
b1001000011100 >
1!
#270
0!
#271
b1001000100000 1
b1001000100000 >
1!
#272
0!
#273
b1001000100100 1
b1001000100100 >
1!
#274
0!
#275
b1001000101000 1
b1001000101000 >
1!
#276
0!
#277
b1001000101100 1
b1001000101100 >
1!
#278
0!
#279
b1001000110000 1
b1001000110000 >
1!
#280
0!
#281
b1001000110100 1
b1001000110100 >
1!
#282
0!
#283
b1001000111000 1
b1001000111000 >
1!
#284
0!
#285
b1001000111100 1
b1001000111100 >
1!
#286
0!
#287
b1001001000000 1
b1001001000000 >
1!
#288
0!
#289
b1001001000100 1
b1001001000100 >
1!
#290
0!
#291
b1001001001000 1
b1001001001000 >
1!
#292
0!
#293
b1001001001100 1
b1001001001100 >
1!
#294
0!
#295
b1001001010000 1
b1001001010000 >
1!
#296
0!
#297
b1001001010100 1
b1001001010100 >
1!
#298
0!
#299
b1001001011000 1
b1001001011000 >
1!
#300
0!
#301
b1001001011100 1
b1001001011100 >
1!
#302
0!
#303
b1001001100000 1
b1001001100000 >
1!
#304
0!
#305
b1001001100100 1
b1001001100100 >
1!
#306
0!
#307
b1001001101000 1
b1001001101000 >
1!
#308
0!
#309
b1001001101100 1
b1001001101100 >
1!
#310
0!
#311
b1001001110000 1
b1001001110000 >
1!
#312
0!
#313
b1001001110100 1
b1001001110100 >
1!
#314
0!
#315
b1001001111000 1
b1001001111000 >
1!
#316
0!
#317
b1001001111100 1
b1001001111100 >
1!
#318
0!
#319
b1001010000000 1
b1001010000000 >
1!
#320
0!
#321
b1001010000100 1
b1001010000100 >
1!
#322
0!
#323
b1001010001000 1
b1001010001000 >
1!
#324
0!
#325
b1001010001100 1
b1001010001100 >
1!
#326
0!
#327
b1001010010000 1
b1001010010000 >
1!
#328
0!
#329
b1001010010100 1
b1001010010100 >
1!
#330
0!
#331
b1001010011000 1
b1001010011000 >
1!
#332
0!
#333
b1001010011100 1
b1001010011100 >
1!
#334
0!
#335
b1001010100000 1
b1001010100000 >
1!
#336
0!
#337
b1001010100100 1
b1001010100100 >
1!
#338
0!
#339
b1001010101000 1
b1001010101000 >
1!
#340
0!
#341
b1001010101100 1
b1001010101100 >
1!
#342
0!
#343
b1001010110000 1
b1001010110000 >
1!
#344
0!
#345
b1001010110100 1
b1001010110100 >
1!
#346
0!
#347
b1001010111000 1
b1001010111000 >
1!
#348
0!
#349
b1001010111100 1
b1001010111100 >
1!
#350
0!
#351
b1001011000000 1
b1001011000000 >
1!
#352
0!
#353
b1001011000100 1
b1001011000100 >
1!
#354
0!
#355
b1001011001000 1
b1001011001000 >
1!
#356
0!
#357
b1001011001100 1
b1001011001100 >
1!
#358
0!
#359
b1001011010000 1
b1001011010000 >
1!
#360
0!
#361
b1001011010100 1
b1001011010100 >
1!
#362
0!
#363
b1001011011000 1
b1001011011000 >
1!
#364
0!
#365
b1001011011100 1
b1001011011100 >
1!
#366
0!
#367
b1001011100000 1
b1001011100000 >
1!
#368
0!
#369
b1001011100100 1
b1001011100100 >
1!
#370
0!
#371
b1001011101000 1
b1001011101000 >
1!
#372
0!
#373
b1001011101100 1
b1001011101100 >
1!
#374
0!
#375
b1001011110000 1
b1001011110000 >
1!
#376
0!
#377
b1001011110100 1
b1001011110100 >
1!
#378
0!
#379
b1001011111000 1
b1001011111000 >
1!
#380
0!
#381
b1001011111100 1
b1001011111100 >
1!
#382
0!
#383
b1001100000000 1
b1001100000000 >
1!
#384
0!
#385
b1001100000100 1
b1001100000100 >
1!
#386
0!
#387
b1001100001000 1
b1001100001000 >
1!
#388
0!
#389
b1001100001100 1
b1001100001100 >
1!
#390
0!
#391
b1001100010000 1
b1001100010000 >
1!
#392
0!
#393
b1001100010100 1
b1001100010100 >
1!
#394
0!
#395
b1001100011000 1
b1001100011000 >
1!
#396
0!
#397
b1001100011100 1
b1001100011100 >
1!
#398
0!
#399
b1001100100000 1
b1001100100000 >
1!
#400
0!
#401
b1001100100100 1
b1001100100100 >
1!
