src/flipflop.v
module FF #(parameter SIZE=32)(
    input [SIZE-1:0] in,
    input write,
    input reset,
    output [SIZE-1:0] out);

    reg [SIZE-1:0] data;

    always @(posedge reset)
        data = 0;

    always @(posedge write)
        data = in;
    
    assign out = data;

endmodule

tests/test_flipflop.v
module test;

    parameter SIZE=2;
    reg reset = 1;

    reg [SIZE-1:0] in;
    wire [SIZE-1:0] out;
    reg write;

    initial begin
        $dumpfile("test.vcd");
        $dumpvars(0, test);

        write = 0;
        #1 reset = 0;

        #2 in = 2'b1;
        #2 write = 1;
        #1 write = 0;

        #2 in = 2'b10;
        #2 write = 1;
        #1 write = 0;

        #4$finish;
    end


    FF #(
        .SIZE(SIZE)
    ) flipflop(
        .reset(reset), 
        .write(write),
        .in(in),
        .out(out));

endmodule // test

graphs/flipflop.vcd
$date
	Mon Jan  1 03:01:49 2018
$end
$version
	Icarus Verilog
$end
$timescale
	1s
$end
$scope module test $end
$var wire 2 ! out [1:0] $end
$var reg 2 " in [1:0] $end
$var reg 1 # reset $end
$var reg 1 $ write $end
$scope module flipflop $end
$var wire 2 % in [1:0] $end
$var wire 2 & out [1:0] $end
$var wire 1 # reset $end
$var wire 1 $ write $end
$var reg 2 ' data [1:0] $end
$upscope $end
$upscope $end
$enddefinitions $end
#0
$dumpvars
b0 '
b0 &
bx %
0$
1#
bx "
b0 !
$end
#1
0#
#3
b1 "
b1 %
#5
b1 !
b1 &
b1 '
1$
#6
0$
#8
b10 "
b10 %
#10
b10 !
b10 &
b10 '
1$
#11
0$
