src/imem.v
module Imem #(parameter ADDRESS_SIZE=32, BOOT_ADDRESS=32'h1000, MEM_SIZE=32'h1000)(
    input reset,
    input [0:ADDRESS_SIZE-1] address,
    output [0:ADDRESS_SIZE-1] instruction);

    reg [7:0] memory [BOOT_ADDRESS:BOOT_ADDRESS+MEM_SIZE];

    initial $readmemb("mem/imem.dat", memory); 

    assign instruction = 
        (address >= BOOT_ADDRESS  && address <= BOOT_ADDRESS + MEM_SIZE - 4)? { memory[address], memory[address+1], memory[address+2], memory[address+3]}
        : 32'h0;


endmodule

tests/test_imem.v
module test;

    parameter ADDRESS_SIZE=32;
    parameter BOOT_ADDRESS=32'h1000;

    reg reset = 1;
    reg [0:ADDRESS_SIZE-1] address = 32'b0;

    wire [0:ADDRESS_SIZE-1] instruction;
    integer i;

    initial begin
        $dumpfile("test.vcd");
        $dumpvars(0, test);

        #1 reset = 0;

        for(i=0; i < 40; ++i) begin
            #10 address = BOOT_ADDRESS + i -5;
            //$display("Instruction for address %h : %b", address, instruction);
        end

        #40 $finish;
    end

    Imem imem(
        .reset(reset), 
        .instruction(instruction),
        .address(address));
        

endmodule // test

graphs/imem.vcd
$date
	Thu Dec 14 18:19:47 2017
$end
$version
	Icarus Verilog
$end
$timescale
	1s
$end
$scope module test $end
$var wire 32 ! instruction [0:31] $end
$var reg 32 " address [0:31] $end
$var reg 1 # reset $end
$var integer 32 $ i [31:0] $end
$scope module imem $end
$var wire 32 % address [0:31] $end
$var wire 1 # reset $end
$var wire 32 & instruction [0:31] $end
$upscope $end
$upscope $end
$enddefinitions $end
#0
$dumpvars
b0 &
b0 %
bx $
1#
b0 "
b0 !
$end
#1
b0 $
0#
#11
b1 $
b111111111011 "
b111111111011 %
#21
b10 $
b111111111100 "
b111111111100 %
#31
b11 $
b111111111101 "
b111111111101 %
#41
b100 $
b111111111110 "
b111111111110 %
#51
b101 $
b111111111111 "
b111111111111 %
#61
b1100000000000000001 !
b1100000000000000001 &
b110 $
b1000000000000 "
b1000000000000 %
#71
b110000000000000000100000000 !
b110000000000000000100000000 &
b111 $
b1000000000001 "
b1000000000001 %
#81
b10000000011000000 !
b10000000011000000 &
b1000 $
b1000000000010 "
b1000000000010 %
#91
b1000000001100000000000000 !
b1000000001100000000000000 &
b1001 $
b1000000000011 "
b1000000000011 %
#101
b110000000000000000000010 !
b110000000000000000000010 &
b1010 $
b1000000000100 "
b1000000000100 %
#111
b11000000000000000000001000011100 !
b11000000000000000000001000011100 &
b1011 $
b1000000000101 "
b1000000000101 %
#121
b100001110000000000 !
b100001110000000000 &
b1100 $
b1000000000110 "
b1000000000110 %
#131
b10000111000000000000000000 !
b10000111000000000000000000 &
b1101 $
b1000000000111 "
b1000000000111 %
#141
b11100000000000000000000000011 !
b11100000000000000000000000011 &
b1110 $
b1000000001000 "
b1000000001000 %
#151
b1100000000 !
b1100000000 &
b1111 $
b1000000001001 "
b1000000001001 %
#161
b110000000000000000 !
b110000000000000000 &
b10000 $
b1000000001010 "
b1000000001010 %
#171
b11000000000000000010000000 !
b11000000000000000010000000 &
b10001 $
b1000000001011 "
b1000000001011 %
#181
b1000000000000100 !
b1000000000000100 &
b10010 $
b1000000001100 "
b1000000001100 %
#191
b100000000000010000000000 !
b100000000000010000000000 &
b10011 $
b1000000001101 "
b1000000001101 %
#201
b10000000000001000000000000000000 !
b10000000000001000000000000000000 &
b10100 $
b1000000001110 "
b1000000001110 %
#211
b100000000000000000000000000 !
b100000000000000000000000000 &
b10101 $
b1000000001111 "
b1000000001111 %
#221
b1 !
b1 &
b10110 $
b1000000010000 "
b1000000010000 %
#231
b100000000 !
b100000000 &
b10111 $
b1000000010001 "
b1000000010001 %
#241
b10000000000000000 !
b10000000000000000 &
b11000 $
b1000000010010 "
b1000000010010 %
#251
b1000000000000000000000000 !
b1000000000000000000000000 &
b11001 $
b1000000010011 "
b1000000010011 %
#261
b10 !
b10 &
b11010 $
b1000000010100 "
b1000000010100 %
#271
b1000000000 !
b1000000000 &
b11011 $
b1000000010101 "
b1000000010101 %
#281
b100000000000000000 !
b100000000000000000 &
b11100 $
b1000000010110 "
b1000000010110 %
#291
b10000000000000000000000000 !
b10000000000000000000000000 &
b11101 $
b1000000010111 "
b1000000010111 %
#301
b11 !
b11 &
b11110 $
b1000000011000 "
b1000000011000 %
#311
b1100000000 !
b1100000000 &
b11111 $
b1000000011001 "
b1000000011001 %
#321
b110000000000000000 !
b110000000000000000 &
b100000 $
b1000000011010 "
b1000000011010 %
#331
b11000000000000000000000000 !
b11000000000000000000000000 &
b100001 $
b1000000011011 "
b1000000011011 %
#341
b100 !
b100 &
b100010 $
b1000000011100 "
b1000000011100 %
#351
b10000000000 !
b10000000000 &
b100011 $
b1000000011101 "
b1000000011101 %
#361
b1000000000000000000 !
b1000000000000000000 &
b100100 $
b1000000011110 "
b1000000011110 %
#371
b100000000000000000000000000 !
b100000000000000000000000000 &
b100101 $
b1000000011111 "
b1000000011111 %
#381
b0 !
b0 &
b100110 $
b1000000100000 "
b1000000100000 %
#391
b100111 $
b1000000100001 "
b1000000100001 %
#401
b101000 $
b1000000100010 "
b1000000100010 %
