src/flipflop.v
module FF #(parameter SIZE=32)(
    input [SIZE-1:0] in,
    input write,
    input reset,
    output [SIZE-1:0] out);

    reg [SIZE-1:0] data;

    always @(posedge reset)
        data = 0;

    always @(posedge write)
        data = in;
    
    assign out = data;

endmodule

src/register_bank.v
module Register_bank #(parameter REGISTER_SIZE=32, ADDRESS_SIZE=5)(
    input clk,
    input reset,
    input [REGISTER_SIZE-1:0] data_in,
    output [REGISTER_SIZE-1:0] data_out1,
    output [REGISTER_SIZE-1:0] data_out2,
    input write,
    input [ADDRESS_SIZE-1:0] addr_out1,
    input [ADDRESS_SIZE-1:0] addr_out2,
    input [ADDRESS_SIZE-1:0] addr_in);

    //reg [REGISTER_SIZE-1:0] bank [(1<<ADDRESS_SIZE)-1:0];
    wire FF_write[(1<<ADDRESS_SIZE)-1:0];
    wire [REGISTER_SIZE-1:0] FF_out[(1<<ADDRESS_SIZE)-1:0];


    generate
        genvar i;
        for(i=0; i < (1<<ADDRESS_SIZE); i=i+1)
        begin
            assign FF_write[i] = addr_in == i? write & clk : 0;
            FF #(
                .SIZE(REGISTER_SIZE)
            ) register(
                .in(data_in),
                .write(FF_write[i]),
                .reset(reset),
                .out(FF_out[i]));
        end
    endgenerate

    assign data_out1 = FF_out[addr_out1];
    assign data_out2 = FF_out[addr_out2];

endmodule

tests/test_register_bank.v
module test;

    parameter REG_ADDRESS_SIZE=5;
    parameter REG_SIZE=8;

    reg [REG_ADDRESS_SIZE-1:0] addr_in = 0;
    reg [REG_ADDRESS_SIZE-1:0] addr_out1 = 0;
    reg [REG_ADDRESS_SIZE-1:0] addr_out2 = 0;
    reg [REG_SIZE-1:0] data_in = 1;
    wire [REG_SIZE-1:0] data_out1;
    wire [REG_SIZE-1:0] data_out2;
    reg write = 1;
    reg reset = 1;
    integer i;

    initial begin
        $dumpfile("test.vcd");
        $dumpvars(0, test);

        #5 addr_in = 1;
        addr_out1 = 1;
        addr_out2 = 0;
        
        for(i = 0; i < (1 <<REG_ADDRESS_SIZE) -1 ; ++i) begin

            #20 addr_in += 1;
            data_in = i;
            addr_out1 += 1;
            addr_out2 += 1;
        end

        #10 $finish;
    end

    reg clk = 0;
    always #10 clk = !clk;

    wire [0:7] value;
    Register_bank #(
        .ADDRESS_SIZE(REG_ADDRESS_SIZE),
        .REGISTER_SIZE(REG_SIZE)
    ) rbank(
        .clk(clk), 
        .reset(reset), 
        .data_in(data_in),
        .data_out1(data_out1), 
        .data_out2(data_out2), 
        .write(write), 
        .addr_in(addr_in),
        .addr_out1(addr_out1),
        .addr_out2(addr_out2));

endmodule // test

graphs/register_bank.vcd
$date
	Mon Jan  1 04:29:37 2018
$end
$version
	Icarus Verilog
$end
$timescale
	1s
$end
$scope module test $end
$var wire 8 ! data_out2 [7:0] $end
$var wire 8 " data_out1 [7:0] $end
$var reg 5 # addr_in [4:0] $end
$var reg 5 $ addr_out1 [4:0] $end
$var reg 5 % addr_out2 [4:0] $end
$var reg 1 & clk $end
$var reg 8 ' data_in [7:0] $end
$var reg 1 ( reset $end
$var reg 1 ) write $end
$var integer 32 * i [31:0] $end
$scope module rbank $end
$var wire 5 + addr_in [4:0] $end
$var wire 5 , addr_out1 [4:0] $end
$var wire 5 - addr_out2 [4:0] $end
$var wire 1 & clk $end
$var wire 8 . data_in [7:0] $end
$var wire 8 / data_out1 [7:0] $end
$var wire 8 0 data_out2 [7:0] $end
$var wire 1 ( reset $end
$var wire 1 ) write $end
$scope begin genblk1[0] $end
$scope module register $end
$var wire 8 1 in [7:0] $end
$var wire 8 2 out [7:0] $end
$var wire 1 ( reset $end
$var wire 1 3 write $end
$var reg 8 4 data [7:0] $end
$upscope $end
$upscope $end
$scope begin genblk1[1] $end
$scope module register $end
$var wire 8 5 in [7:0] $end
$var wire 8 6 out [7:0] $end
$var wire 1 ( reset $end
$var wire 1 7 write $end
$var reg 8 8 data [7:0] $end
$upscope $end
$upscope $end
$scope begin genblk1[2] $end
$scope module register $end
$var wire 8 9 in [7:0] $end
$var wire 8 : out [7:0] $end
$var wire 1 ( reset $end
$var wire 1 ; write $end
$var reg 8 < data [7:0] $end
$upscope $end
$upscope $end
$scope begin genblk1[3] $end
$scope module register $end
$var wire 8 = in [7:0] $end
$var wire 8 > out [7:0] $end
$var wire 1 ( reset $end
$var wire 1 ? write $end
$var reg 8 @ data [7:0] $end
$upscope $end
$upscope $end
$scope begin genblk1[4] $end
$scope module register $end
$var wire 8 A in [7:0] $end
$var wire 8 B out [7:0] $end
$var wire 1 ( reset $end
$var wire 1 C write $end
$var reg 8 D data [7:0] $end
$upscope $end
$upscope $end
$scope begin genblk1[5] $end
$scope module register $end
$var wire 8 E in [7:0] $end
$var wire 8 F out [7:0] $end
$var wire 1 ( reset $end
$var wire 1 G write $end
$var reg 8 H data [7:0] $end
$upscope $end
$upscope $end
$scope begin genblk1[6] $end
$scope module register $end
$var wire 8 I in [7:0] $end
$var wire 8 J out [7:0] $end
$var wire 1 ( reset $end
$var wire 1 K write $end
$var reg 8 L data [7:0] $end
$upscope $end
$upscope $end
$scope begin genblk1[7] $end
$scope module register $end
$var wire 8 M in [7:0] $end
$var wire 8 N out [7:0] $end
$var wire 1 ( reset $end
$var wire 1 O write $end
$var reg 8 P data [7:0] $end
$upscope $end
$upscope $end
$scope begin genblk1[8] $end
$scope module register $end
$var wire 8 Q in [7:0] $end
$var wire 8 R out [7:0] $end
$var wire 1 ( reset $end
$var wire 1 S write $end
$var reg 8 T data [7:0] $end
$upscope $end
$upscope $end
$scope begin genblk1[9] $end
$scope module register $end
$var wire 8 U in [7:0] $end
$var wire 8 V out [7:0] $end
$var wire 1 ( reset $end
$var wire 1 W write $end
$var reg 8 X data [7:0] $end
$upscope $end
$upscope $end
$scope begin genblk1[10] $end
$scope module register $end
$var wire 8 Y in [7:0] $end
$var wire 8 Z out [7:0] $end
$var wire 1 ( reset $end
$var wire 1 [ write $end
$var reg 8 \ data [7:0] $end
$upscope $end
$upscope $end
$scope begin genblk1[11] $end
$scope module register $end
$var wire 8 ] in [7:0] $end
$var wire 8 ^ out [7:0] $end
$var wire 1 ( reset $end
$var wire 1 _ write $end
$var reg 8 ` data [7:0] $end
$upscope $end
$upscope $end
$scope begin genblk1[12] $end
$scope module register $end
$var wire 8 a in [7:0] $end
$var wire 8 b out [7:0] $end
$var wire 1 ( reset $end
$var wire 1 c write $end
$var reg 8 d data [7:0] $end
$upscope $end
$upscope $end
$scope begin genblk1[13] $end
$scope module register $end
$var wire 8 e in [7:0] $end
$var wire 8 f out [7:0] $end
$var wire 1 ( reset $end
$var wire 1 g write $end
$var reg 8 h data [7:0] $end
$upscope $end
$upscope $end
$scope begin genblk1[14] $end
$scope module register $end
$var wire 8 i in [7:0] $end
$var wire 8 j out [7:0] $end
$var wire 1 ( reset $end
$var wire 1 k write $end
$var reg 8 l data [7:0] $end
$upscope $end
$upscope $end
$scope begin genblk1[15] $end
$scope module register $end
$var wire 8 m in [7:0] $end
$var wire 8 n out [7:0] $end
$var wire 1 ( reset $end
$var wire 1 o write $end
$var reg 8 p data [7:0] $end
$upscope $end
$upscope $end
$scope begin genblk1[16] $end
$scope module register $end
$var wire 8 q in [7:0] $end
$var wire 8 r out [7:0] $end
$var wire 1 ( reset $end
$var wire 1 s write $end
$var reg 8 t data [7:0] $end
$upscope $end
$upscope $end
$scope begin genblk1[17] $end
$scope module register $end
$var wire 8 u in [7:0] $end
$var wire 8 v out [7:0] $end
$var wire 1 ( reset $end
$var wire 1 w write $end
$var reg 8 x data [7:0] $end
$upscope $end
$upscope $end
$scope begin genblk1[18] $end
$scope module register $end
$var wire 8 y in [7:0] $end
$var wire 8 z out [7:0] $end
$var wire 1 ( reset $end
$var wire 1 { write $end
$var reg 8 | data [7:0] $end
$upscope $end
$upscope $end
$scope begin genblk1[19] $end
$scope module register $end
$var wire 8 } in [7:0] $end
$var wire 8 ~ out [7:0] $end
$var wire 1 ( reset $end
$var wire 1 !" write $end
$var reg 8 "" data [7:0] $end
$upscope $end
$upscope $end
$scope begin genblk1[20] $end
$scope module register $end
$var wire 8 #" in [7:0] $end
$var wire 8 $" out [7:0] $end
$var wire 1 ( reset $end
$var wire 1 %" write $end
$var reg 8 &" data [7:0] $end
$upscope $end
$upscope $end
$scope begin genblk1[21] $end
$scope module register $end
$var wire 8 '" in [7:0] $end
$var wire 8 (" out [7:0] $end
$var wire 1 ( reset $end
$var wire 1 )" write $end
$var reg 8 *" data [7:0] $end
$upscope $end
$upscope $end
$scope begin genblk1[22] $end
$scope module register $end
$var wire 8 +" in [7:0] $end
$var wire 8 ," out [7:0] $end
$var wire 1 ( reset $end
$var wire 1 -" write $end
$var reg 8 ." data [7:0] $end
$upscope $end
$upscope $end
$scope begin genblk1[23] $end
$scope module register $end
$var wire 8 /" in [7:0] $end
$var wire 8 0" out [7:0] $end
$var wire 1 ( reset $end
$var wire 1 1" write $end
$var reg 8 2" data [7:0] $end
$upscope $end
$upscope $end
$scope begin genblk1[24] $end
$scope module register $end
$var wire 8 3" in [7:0] $end
$var wire 8 4" out [7:0] $end
$var wire 1 ( reset $end
$var wire 1 5" write $end
$var reg 8 6" data [7:0] $end
$upscope $end
$upscope $end
$scope begin genblk1[25] $end
$scope module register $end
$var wire 8 7" in [7:0] $end
$var wire 8 8" out [7:0] $end
$var wire 1 ( reset $end
$var wire 1 9" write $end
$var reg 8 :" data [7:0] $end
$upscope $end
$upscope $end
$scope begin genblk1[26] $end
$scope module register $end
$var wire 8 ;" in [7:0] $end
$var wire 8 <" out [7:0] $end
$var wire 1 ( reset $end
$var wire 1 =" write $end
$var reg 8 >" data [7:0] $end
$upscope $end
$upscope $end
$scope begin genblk1[27] $end
$scope module register $end
$var wire 8 ?" in [7:0] $end
$var wire 8 @" out [7:0] $end
$var wire 1 ( reset $end
$var wire 1 A" write $end
$var reg 8 B" data [7:0] $end
$upscope $end
$upscope $end
$scope begin genblk1[28] $end
$scope module register $end
$var wire 8 C" in [7:0] $end
$var wire 8 D" out [7:0] $end
$var wire 1 ( reset $end
$var wire 1 E" write $end
$var reg 8 F" data [7:0] $end
$upscope $end
$upscope $end
$scope begin genblk1[29] $end
$scope module register $end
$var wire 8 G" in [7:0] $end
$var wire 8 H" out [7:0] $end
$var wire 1 ( reset $end
$var wire 1 I" write $end
$var reg 8 J" data [7:0] $end
$upscope $end
$upscope $end
$scope begin genblk1[30] $end
$scope module register $end
$var wire 8 K" in [7:0] $end
$var wire 8 L" out [7:0] $end
$var wire 1 ( reset $end
$var wire 1 M" write $end
$var reg 8 N" data [7:0] $end
$upscope $end
$upscope $end
$scope begin genblk1[31] $end
$scope module register $end
$var wire 8 O" in [7:0] $end
$var wire 8 P" out [7:0] $end
$var wire 1 ( reset $end
$var wire 1 Q" write $end
$var reg 8 R" data [7:0] $end
$upscope $end
$upscope $end
$upscope $end
$upscope $end
$enddefinitions $end
#0
$dumpvars
b0 R"
0Q"
b0 P"
b1 O"
b0 N"
0M"
b0 L"
b1 K"
b0 J"
0I"
b0 H"
b1 G"
b0 F"
0E"
b0 D"
b1 C"
b0 B"
0A"
b0 @"
b1 ?"
b0 >"
0="
b0 <"
b1 ;"
b0 :"
09"
b0 8"
b1 7"
b0 6"
05"
b0 4"
b1 3"
b0 2"
01"
b0 0"
b1 /"
b0 ."
0-"
b0 ,"
b1 +"
b0 *"
0)"
b0 ("
b1 '"
b0 &"
0%"
b0 $"
b1 #"
b0 ""
0!"
b0 ~
b1 }
b0 |
0{
b0 z
b1 y
b0 x
0w
b0 v
b1 u
b0 t
0s
b0 r
b1 q
b0 p
0o
b0 n
b1 m
b0 l
0k
b0 j
b1 i
b0 h
0g
b0 f
b1 e
b0 d
0c
b0 b
b1 a
b0 `
0_
b0 ^
b1 ]
b0 \
0[
b0 Z
b1 Y
b0 X
0W
b0 V
b1 U
b0 T
0S
b0 R
b1 Q
b0 P
0O
b0 N
b1 M
b0 L
0K
b0 J
b1 I
b0 H
0G
b0 F
b1 E
b0 D
0C
b0 B
b1 A
b0 @
0?
b0 >
b1 =
b0 <
0;
b0 :
b1 9
b0 8
07
b0 6
b1 5
b0 4
03
b0 2
b1 1
b0 0
b0 /
b1 .
b0 -
b0 ,
b0 +
bx *
1)
1(
b1 '
0&
b0 %
b0 $
b0 #
b0 "
b0 !
$end
#5
b0 *
b1 $
b1 ,
b1 #
b1 +
#10
b1 6
b1 "
b1 /
b1 8
17
1&
#20
07
0&
#25
b1 *
b1 !
b1 0
b1 %
b1 -
b0 "
b0 /
b10 $
b10 ,
b0 '
b0 .
b0 1
b0 5
b0 9
b0 =
b0 A
b0 E
b0 I
b0 M
b0 Q
b0 U
b0 Y
b0 ]
b0 a
b0 e
b0 i
b0 m
b0 q
b0 u
b0 y
b0 }
b0 #"
b0 '"
b0 +"
b0 /"
b0 3"
b0 7"
b0 ;"
b0 ?"
b0 C"
b0 G"
b0 K"
b0 O"
b10 #
b10 +
#30
1;
1&
#40
0;
0&
#45
b10 *
b0 !
b0 0
b10 %
b10 -
b11 $
b11 ,
b1 '
b1 .
b1 1
b1 5
b1 9
b1 =
b1 A
b1 E
b1 I
b1 M
b1 Q
b1 U
b1 Y
b1 ]
b1 a
b1 e
b1 i
b1 m
b1 q
b1 u
b1 y
b1 }
b1 #"
b1 '"
b1 +"
b1 /"
b1 3"
b1 7"
b1 ;"
b1 ?"
b1 C"
b1 G"
b1 K"
b1 O"
b11 #
b11 +
#50
b1 >
b1 "
b1 /
b1 @
1?
1&
#60
0?
0&
#65
b11 *
b1 !
b1 0
b11 %
b11 -
b0 "
b0 /
b100 $
b100 ,
b10 '
b10 .
b10 1
b10 5
b10 9
b10 =
b10 A
b10 E
b10 I
b10 M
b10 Q
b10 U
b10 Y
b10 ]
b10 a
b10 e
b10 i
b10 m
b10 q
b10 u
b10 y
b10 }
b10 #"
b10 '"
b10 +"
b10 /"
b10 3"
b10 7"
b10 ;"
b10 ?"
b10 C"
b10 G"
b10 K"
b10 O"
b100 #
b100 +
#70
b10 B
b10 "
b10 /
b10 D
1C
1&
#80
0C
0&
#85
b100 *
b10 !
b10 0
b100 %
b100 -
b0 "
b0 /
b101 $
b101 ,
b11 '
b11 .
b11 1
b11 5
b11 9
b11 =
b11 A
b11 E
b11 I
b11 M
b11 Q
b11 U
b11 Y
b11 ]
b11 a
b11 e
b11 i
b11 m
b11 q
b11 u
b11 y
b11 }
b11 #"
b11 '"
b11 +"
b11 /"
b11 3"
b11 7"
b11 ;"
b11 ?"
b11 C"
b11 G"
b11 K"
b11 O"
b101 #
b101 +
#90
b11 F
b11 "
b11 /
b11 H
1G
1&
#100
0G
0&
#105
b101 *
b11 !
b11 0
b101 %
b101 -
b0 "
b0 /
b110 $
b110 ,
b100 '
b100 .
b100 1
b100 5
b100 9
b100 =
b100 A
b100 E
b100 I
b100 M
b100 Q
b100 U
b100 Y
b100 ]
b100 a
b100 e
b100 i
b100 m
b100 q
b100 u
b100 y
b100 }
b100 #"
b100 '"
b100 +"
b100 /"
b100 3"
b100 7"
b100 ;"
b100 ?"
b100 C"
b100 G"
b100 K"
b100 O"
b110 #
b110 +
#110
b100 J
b100 "
b100 /
b100 L
1K
1&
#120
0K
0&
#125
b110 *
b100 !
b100 0
b110 %
b110 -
b0 "
b0 /
b111 $
b111 ,
b101 '
b101 .
b101 1
b101 5
b101 9
b101 =
b101 A
b101 E
b101 I
b101 M
b101 Q
b101 U
b101 Y
b101 ]
b101 a
b101 e
b101 i
b101 m
b101 q
b101 u
b101 y
b101 }
b101 #"
b101 '"
b101 +"
b101 /"
b101 3"
b101 7"
b101 ;"
b101 ?"
b101 C"
b101 G"
b101 K"
b101 O"
b111 #
b111 +
#130
b101 N
b101 "
b101 /
b101 P
1O
1&
#140
0O
0&
#145
b111 *
b101 !
b101 0
b111 %
b111 -
b0 "
b0 /
b1000 $
b1000 ,
b110 '
b110 .
b110 1
b110 5
b110 9
b110 =
b110 A
b110 E
b110 I
b110 M
b110 Q
b110 U
b110 Y
b110 ]
b110 a
b110 e
b110 i
b110 m
b110 q
b110 u
b110 y
b110 }
b110 #"
b110 '"
b110 +"
b110 /"
b110 3"
b110 7"
b110 ;"
b110 ?"
b110 C"
b110 G"
b110 K"
b110 O"
b1000 #
b1000 +
#150
b110 R
b110 "
b110 /
b110 T
1S
1&
#160
0S
0&
#165
b1000 *
b110 !
b110 0
b1000 %
b1000 -
b0 "
b0 /
b1001 $
b1001 ,
b111 '
b111 .
b111 1
b111 5
b111 9
b111 =
b111 A
b111 E
b111 I
b111 M
b111 Q
b111 U
b111 Y
b111 ]
b111 a
b111 e
b111 i
b111 m
b111 q
b111 u
b111 y
b111 }
b111 #"
b111 '"
b111 +"
b111 /"
b111 3"
b111 7"
b111 ;"
b111 ?"
b111 C"
b111 G"
b111 K"
b111 O"
b1001 #
b1001 +
#170
b111 V
b111 "
b111 /
b111 X
1W
1&
#180
0W
0&
#185
b1001 *
b111 !
b111 0
b1001 %
b1001 -
b0 "
b0 /
b1010 $
b1010 ,
b1000 '
b1000 .
b1000 1
b1000 5
b1000 9
b1000 =
b1000 A
b1000 E
b1000 I
b1000 M
b1000 Q
b1000 U
b1000 Y
b1000 ]
b1000 a
b1000 e
b1000 i
b1000 m
b1000 q
b1000 u
b1000 y
b1000 }
b1000 #"
b1000 '"
b1000 +"
b1000 /"
b1000 3"
b1000 7"
b1000 ;"
b1000 ?"
b1000 C"
b1000 G"
b1000 K"
b1000 O"
b1010 #
b1010 +
#190
b1000 Z
b1000 "
b1000 /
b1000 \
1[
1&
#200
0[
0&
#205
b1010 *
b1000 !
b1000 0
b1010 %
b1010 -
b0 "
b0 /
b1011 $
b1011 ,
b1001 '
b1001 .
b1001 1
b1001 5
b1001 9
b1001 =
b1001 A
b1001 E
b1001 I
b1001 M
b1001 Q
b1001 U
b1001 Y
b1001 ]
b1001 a
b1001 e
b1001 i
b1001 m
b1001 q
b1001 u
b1001 y
b1001 }
b1001 #"
b1001 '"
b1001 +"
b1001 /"
b1001 3"
b1001 7"
b1001 ;"
b1001 ?"
b1001 C"
b1001 G"
b1001 K"
b1001 O"
b1011 #
b1011 +
#210
b1001 ^
b1001 "
b1001 /
b1001 `
1_
1&
#220
0_
0&
#225
b1011 *
b1001 !
b1001 0
b1011 %
b1011 -
b0 "
b0 /
b1100 $
b1100 ,
b1010 '
b1010 .
b1010 1
b1010 5
b1010 9
b1010 =
b1010 A
b1010 E
b1010 I
b1010 M
b1010 Q
b1010 U
b1010 Y
b1010 ]
b1010 a
b1010 e
b1010 i
b1010 m
b1010 q
b1010 u
b1010 y
b1010 }
b1010 #"
b1010 '"
b1010 +"
b1010 /"
b1010 3"
b1010 7"
b1010 ;"
b1010 ?"
b1010 C"
b1010 G"
b1010 K"
b1010 O"
b1100 #
b1100 +
#230
b1010 b
b1010 "
b1010 /
b1010 d
1c
1&
#240
0c
0&
#245
b1100 *
b1010 !
b1010 0
b1100 %
b1100 -
b0 "
b0 /
b1101 $
b1101 ,
b1011 '
b1011 .
b1011 1
b1011 5
b1011 9
b1011 =
b1011 A
b1011 E
b1011 I
b1011 M
b1011 Q
b1011 U
b1011 Y
b1011 ]
b1011 a
b1011 e
b1011 i
b1011 m
b1011 q
b1011 u
b1011 y
b1011 }
b1011 #"
b1011 '"
b1011 +"
b1011 /"
b1011 3"
b1011 7"
b1011 ;"
b1011 ?"
b1011 C"
b1011 G"
b1011 K"
b1011 O"
b1101 #
b1101 +
#250
b1011 f
b1011 "
b1011 /
b1011 h
1g
1&
#260
0g
0&
#265
b1101 *
b1011 !
b1011 0
b1101 %
b1101 -
b0 "
b0 /
b1110 $
b1110 ,
b1100 '
b1100 .
b1100 1
b1100 5
b1100 9
b1100 =
b1100 A
b1100 E
b1100 I
b1100 M
b1100 Q
b1100 U
b1100 Y
b1100 ]
b1100 a
b1100 e
b1100 i
b1100 m
b1100 q
b1100 u
b1100 y
b1100 }
b1100 #"
b1100 '"
b1100 +"
b1100 /"
b1100 3"
b1100 7"
b1100 ;"
b1100 ?"
b1100 C"
b1100 G"
b1100 K"
b1100 O"
b1110 #
b1110 +
#270
b1100 j
b1100 "
b1100 /
b1100 l
1k
1&
#280
0k
0&
#285
b1110 *
b1100 !
b1100 0
b1110 %
b1110 -
b0 "
b0 /
b1111 $
b1111 ,
b1101 '
b1101 .
b1101 1
b1101 5
b1101 9
b1101 =
b1101 A
b1101 E
b1101 I
b1101 M
b1101 Q
b1101 U
b1101 Y
b1101 ]
b1101 a
b1101 e
b1101 i
b1101 m
b1101 q
b1101 u
b1101 y
b1101 }
b1101 #"
b1101 '"
b1101 +"
b1101 /"
b1101 3"
b1101 7"
b1101 ;"
b1101 ?"
b1101 C"
b1101 G"
b1101 K"
b1101 O"
b1111 #
b1111 +
#290
b1101 n
b1101 "
b1101 /
b1101 p
1o
1&
#300
0o
0&
#305
b1111 *
b1101 !
b1101 0
b1111 %
b1111 -
b0 "
b0 /
b10000 $
b10000 ,
b1110 '
b1110 .
b1110 1
b1110 5
b1110 9
b1110 =
b1110 A
b1110 E
b1110 I
b1110 M
b1110 Q
b1110 U
b1110 Y
b1110 ]
b1110 a
b1110 e
b1110 i
b1110 m
b1110 q
b1110 u
b1110 y
b1110 }
b1110 #"
b1110 '"
b1110 +"
b1110 /"
b1110 3"
b1110 7"
b1110 ;"
b1110 ?"
b1110 C"
b1110 G"
b1110 K"
b1110 O"
b10000 #
b10000 +
#310
b1110 r
b1110 "
b1110 /
b1110 t
1s
1&
#320
0s
0&
#325
b10000 *
b1110 !
b1110 0
b10000 %
b10000 -
b0 "
b0 /
b10001 $
b10001 ,
b1111 '
b1111 .
b1111 1
b1111 5
b1111 9
b1111 =
b1111 A
b1111 E
b1111 I
b1111 M
b1111 Q
b1111 U
b1111 Y
b1111 ]
b1111 a
b1111 e
b1111 i
b1111 m
b1111 q
b1111 u
b1111 y
b1111 }
b1111 #"
b1111 '"
b1111 +"
b1111 /"
b1111 3"
b1111 7"
b1111 ;"
b1111 ?"
b1111 C"
b1111 G"
b1111 K"
b1111 O"
b10001 #
b10001 +
#330
b1111 v
b1111 "
b1111 /
b1111 x
1w
1&
#340
0w
0&
#345
b10001 *
b1111 !
b1111 0
b10001 %
b10001 -
b0 "
b0 /
b10010 $
b10010 ,
b10000 '
b10000 .
b10000 1
b10000 5
b10000 9
b10000 =
b10000 A
b10000 E
b10000 I
b10000 M
b10000 Q
b10000 U
b10000 Y
b10000 ]
b10000 a
b10000 e
b10000 i
b10000 m
b10000 q
b10000 u
b10000 y
b10000 }
b10000 #"
b10000 '"
b10000 +"
b10000 /"
b10000 3"
b10000 7"
b10000 ;"
b10000 ?"
b10000 C"
b10000 G"
b10000 K"
b10000 O"
b10010 #
b10010 +
#350
b10000 z
b10000 "
b10000 /
b10000 |
1{
1&
#360
0{
0&
#365
b10010 *
b10000 !
b10000 0
b10010 %
b10010 -
b0 "
b0 /
b10011 $
b10011 ,
b10001 '
b10001 .
b10001 1
b10001 5
b10001 9
b10001 =
b10001 A
b10001 E
b10001 I
b10001 M
b10001 Q
b10001 U
b10001 Y
b10001 ]
b10001 a
b10001 e
b10001 i
b10001 m
b10001 q
b10001 u
b10001 y
b10001 }
b10001 #"
b10001 '"
b10001 +"
b10001 /"
b10001 3"
b10001 7"
b10001 ;"
b10001 ?"
b10001 C"
b10001 G"
b10001 K"
b10001 O"
b10011 #
b10011 +
#370
b10001 ~
b10001 "
b10001 /
b10001 ""
1!"
1&
#380
0!"
0&
#385
b10011 *
b10001 !
b10001 0
b10011 %
b10011 -
b0 "
b0 /
b10100 $
b10100 ,
b10010 '
b10010 .
b10010 1
b10010 5
b10010 9
b10010 =
b10010 A
b10010 E
b10010 I
b10010 M
b10010 Q
b10010 U
b10010 Y
b10010 ]
b10010 a
b10010 e
b10010 i
b10010 m
b10010 q
b10010 u
b10010 y
b10010 }
b10010 #"
b10010 '"
b10010 +"
b10010 /"
b10010 3"
b10010 7"
b10010 ;"
b10010 ?"
b10010 C"
b10010 G"
b10010 K"
b10010 O"
b10100 #
b10100 +
#390
b10010 $"
b10010 "
b10010 /
b10010 &"
1%"
1&
#400
0%"
0&
#405
b10100 *
b10010 !
b10010 0
b10100 %
b10100 -
b0 "
b0 /
b10101 $
b10101 ,
b10011 '
b10011 .
b10011 1
b10011 5
b10011 9
b10011 =
b10011 A
b10011 E
b10011 I
b10011 M
b10011 Q
b10011 U
b10011 Y
b10011 ]
b10011 a
b10011 e
b10011 i
b10011 m
b10011 q
b10011 u
b10011 y
b10011 }
b10011 #"
b10011 '"
b10011 +"
b10011 /"
b10011 3"
b10011 7"
b10011 ;"
b10011 ?"
b10011 C"
b10011 G"
b10011 K"
b10011 O"
b10101 #
b10101 +
#410
b10011 ("
b10011 "
b10011 /
b10011 *"
1)"
1&
#420
0)"
0&
#425
b10101 *
b10011 !
b10011 0
b10101 %
b10101 -
b0 "
b0 /
b10110 $
b10110 ,
b10100 '
b10100 .
b10100 1
b10100 5
b10100 9
b10100 =
b10100 A
b10100 E
b10100 I
b10100 M
b10100 Q
b10100 U
b10100 Y
b10100 ]
b10100 a
b10100 e
b10100 i
b10100 m
b10100 q
b10100 u
b10100 y
b10100 }
b10100 #"
b10100 '"
b10100 +"
b10100 /"
b10100 3"
b10100 7"
b10100 ;"
b10100 ?"
b10100 C"
b10100 G"
b10100 K"
b10100 O"
b10110 #
b10110 +
#430
b10100 ,"
b10100 "
b10100 /
b10100 ."
1-"
1&
#440
0-"
0&
#445
b10110 *
b10100 !
b10100 0
b10110 %
b10110 -
b0 "
b0 /
b10111 $
b10111 ,
b10101 '
b10101 .
b10101 1
b10101 5
b10101 9
b10101 =
b10101 A
b10101 E
b10101 I
b10101 M
b10101 Q
b10101 U
b10101 Y
b10101 ]
b10101 a
b10101 e
b10101 i
b10101 m
b10101 q
b10101 u
b10101 y
b10101 }
b10101 #"
b10101 '"
b10101 +"
b10101 /"
b10101 3"
b10101 7"
b10101 ;"
b10101 ?"
b10101 C"
b10101 G"
b10101 K"
b10101 O"
b10111 #
b10111 +
#450
b10101 0"
b10101 "
b10101 /
b10101 2"
11"
1&
#460
01"
0&
#465
b10111 *
b10101 !
b10101 0
b10111 %
b10111 -
b0 "
b0 /
b11000 $
b11000 ,
b10110 '
b10110 .
b10110 1
b10110 5
b10110 9
b10110 =
b10110 A
b10110 E
b10110 I
b10110 M
b10110 Q
b10110 U
b10110 Y
b10110 ]
b10110 a
b10110 e
b10110 i
b10110 m
b10110 q
b10110 u
b10110 y
b10110 }
b10110 #"
b10110 '"
b10110 +"
b10110 /"
b10110 3"
b10110 7"
b10110 ;"
b10110 ?"
b10110 C"
b10110 G"
b10110 K"
b10110 O"
b11000 #
b11000 +
#470
b10110 4"
b10110 "
b10110 /
b10110 6"
15"
1&
#480
05"
0&
#485
b11000 *
b10110 !
b10110 0
b11000 %
b11000 -
b0 "
b0 /
b11001 $
b11001 ,
b10111 '
b10111 .
b10111 1
b10111 5
b10111 9
b10111 =
b10111 A
b10111 E
b10111 I
b10111 M
b10111 Q
b10111 U
b10111 Y
b10111 ]
b10111 a
b10111 e
b10111 i
b10111 m
b10111 q
b10111 u
b10111 y
b10111 }
b10111 #"
b10111 '"
b10111 +"
b10111 /"
b10111 3"
b10111 7"
b10111 ;"
b10111 ?"
b10111 C"
b10111 G"
b10111 K"
b10111 O"
b11001 #
b11001 +
#490
b10111 8"
b10111 "
b10111 /
b10111 :"
19"
1&
#500
09"
0&
#505
b11001 *
b10111 !
b10111 0
b11001 %
b11001 -
b0 "
b0 /
b11010 $
b11010 ,
b11000 '
b11000 .
b11000 1
b11000 5
b11000 9
b11000 =
b11000 A
b11000 E
b11000 I
b11000 M
b11000 Q
b11000 U
b11000 Y
b11000 ]
b11000 a
b11000 e
b11000 i
b11000 m
b11000 q
b11000 u
b11000 y
b11000 }
b11000 #"
b11000 '"
b11000 +"
b11000 /"
b11000 3"
b11000 7"
b11000 ;"
b11000 ?"
b11000 C"
b11000 G"
b11000 K"
b11000 O"
b11010 #
b11010 +
#510
b11000 <"
b11000 "
b11000 /
b11000 >"
1="
1&
#520
0="
0&
#525
b11010 *
b11000 !
b11000 0
b11010 %
b11010 -
b0 "
b0 /
b11011 $
b11011 ,
b11001 '
b11001 .
b11001 1
b11001 5
b11001 9
b11001 =
b11001 A
b11001 E
b11001 I
b11001 M
b11001 Q
b11001 U
b11001 Y
b11001 ]
b11001 a
b11001 e
b11001 i
b11001 m
b11001 q
b11001 u
b11001 y
b11001 }
b11001 #"
b11001 '"
b11001 +"
b11001 /"
b11001 3"
b11001 7"
b11001 ;"
b11001 ?"
b11001 C"
b11001 G"
b11001 K"
b11001 O"
b11011 #
b11011 +
#530
b11001 @"
b11001 "
b11001 /
b11001 B"
1A"
1&
#540
0A"
0&
#545
b11011 *
b11001 !
b11001 0
b11011 %
b11011 -
b0 "
b0 /
b11100 $
b11100 ,
b11010 '
b11010 .
b11010 1
b11010 5
b11010 9
b11010 =
b11010 A
b11010 E
b11010 I
b11010 M
b11010 Q
b11010 U
b11010 Y
b11010 ]
b11010 a
b11010 e
b11010 i
b11010 m
b11010 q
b11010 u
b11010 y
b11010 }
b11010 #"
b11010 '"
b11010 +"
b11010 /"
b11010 3"
b11010 7"
b11010 ;"
b11010 ?"
b11010 C"
b11010 G"
b11010 K"
b11010 O"
b11100 #
b11100 +
#550
b11010 D"
b11010 "
b11010 /
b11010 F"
1E"
1&
#560
0E"
0&
