src/flipflop.v
module FF #(parameter SIZE=32, RESET_VALUE=0)(
    input [SIZE-1:0] in,
    input write,
    input erase,
    input stall,
    input reset,
    output [SIZE-1:0] out);

    reg [SIZE-1:0] data;

    always @(posedge reset)
        data = RESET_VALUE;

    always @(posedge write)
        if(!stall)
        begin
            if (!erase)
                data = #1 in;
            else
                data = #1 RESET_VALUE;
        end

    assign out = data;

endmodule

src/ROB.v
module ROB #(parameter REGISTER_SIZE=32, REG_ADDRESS_SIZE=5, ID_SIZE=1)(

    input [ID_SIZE-1: 0] port1_id,
    input [REG_ADDRESS_SIZE-1:0] port1_address,
    input [REGISTER_SIZE-1:0] port1_data,
    input port1_w,
    input port1_req,
    output port1_stall,

    input [ID_SIZE-1: 0] port2_id,
    input [REG_ADDRESS_SIZE-1:0] port2_address,
    input [REGISTER_SIZE-1:0] port2_data,
    input port2_w,
    input port2_req,
    output port2_stall,

    input [ID_SIZE-1:0]tail,
    output assignment_stall,
    output [REG_ADDRESS_SIZE-1:0]current_address,
    output [REGISTER_SIZE-1:0] current_data,
    output current_write,
    input clk,
    input reset);

    reg [ID_SIZE-1:0]head; 
    reg empty = 1;

    wire [REGISTER_SIZE-1:0] data [(1<<ID_SIZE)-1:0];
    wire [REG_ADDRESS_SIZE-1:0] address [(1<<ID_SIZE)-1:0];
    wire [(1<<ID_SIZE)-1:0] we;
    wire [(1<<ID_SIZE)-1:0] valid;

    // returns id1 < id2
    function compare_ids;
        input [ID_SIZE-1:0] id1, id2, head;
        begin
            compare_ids =
                id1 >= head?
                id2 >= head? 
                id2 > id1? 1
                : 0
                : 1
                : id2 >= head? 0
                : id2 > id1? 1
                : 0;

        end
    endfunction


    wire selected_port =
        port1_req?
        port2_req?
        compare_ids(port1_id, port2_id, head)? 0
        : 1
        : 0
        : 1;

    wire [REGISTER_SIZE-1: 0] selected_port_data; 
    wire [REG_ADDRESS_SIZE-1:0] selected_port_address; 
    wire [ID_SIZE-1:0]selected_port_id;
    wire selected_port_req;
    wire selected_port_w;

    generate
        genvar i;
        for(i=0; i < (1<<(ID_SIZE)); i = i+1)
        begin

            FF #(REGISTER_SIZE+REG_ADDRESS_SIZE+1+1) slot(
                .in({selected_port_data, selected_port_address, selected_port_w, 1'b1}),
                .out({data[i], address[i], we[i], valid[i]}),
                .write(clk),
                .stall((!selected_port_req || selected_port_id != i) && !(valid[i] && (head == i))),
                .erase(valid[i] && (head == i)),
                .reset(reset)
                );
        end
    endgenerate

    assign selected_port_data =
        selected_port? port2_data
        : port1_data;

    assign selected_port_id =
        selected_port? port2_id
        : port1_id;

    assign selected_port_w =
        selected_port? port2_w
        : port1_w;

    assign selected_port_req =
        selected_port? port2_req
        : port1_req;

    assign selected_port_address =
        selected_port? port2_address
        : port1_address;

    assign port1_stall = (selected_port != 0) && port1_req;
    assign port2_stall = (selected_port != 1) && port2_req;

    always @(posedge clk)
    begin
        if (valid[head])
        begin
            if(head+1 == tail)
            begin
                #1 empty = 1;
            end
            #1 head <= head+1;

        end
        else if(head != tail) #1 empty = 0;
    end

    always @reset
        head = 0;

    assign current_address = address[head];
    assign current_data = data[head];
    assign current_write = we[head] && valid[head];

    assign assignment_stall = (head == tail) && !empty;

endmodule

tests/test_ROB.v
module test #(parameter REGISTER_SIZE=32, REG_ADDRESS_SIZE=5, ID_SIZE=1)();

    reg [ID_SIZE-1: 0] port1_id;
    reg [REG_ADDRESS_SIZE-1:0] port1_address;
    reg [REGISTER_SIZE-1:0] port1_data;
    reg port1_w;
    reg port1_req;
    wire port1_stall;
    reg [ID_SIZE-1: 0] port2_id;
    reg [REG_ADDRESS_SIZE-1:0] port2_address;
    reg [REGISTER_SIZE-1:0] port2_data;
    reg port2_w;
    reg port2_req;
    wire port2_stall;

    wire tail;
    reg clk;

    reg reset; 

    initial clk = 0;
    always #10 clk = !clk;

    initial begin
        $dumpfile("test.vcd");
        $dumpvars(0, test);
        reset =1;

        port1_req=0;
        port2_req=0;

        #20 reset = 0;

        #20 port1_id = 1;
        port1_w=1;
        port1_req=1;
        port1_address=5'b1;
        port1_data = 1;

        #40 port1_req = 0;
        port2_id=0;
        port2_req=1;
        port2_w=0;
        port2_address=0;
        port2_data=1;

        #40 port1_req = 1;

        #50 $finish;

    end

    ROB rob(
        .clk(clk),
        .reset(reset),
        .port1_id(port1_id),
        .port1_address(port1_address),
        .port1_req(port1_req),
        .port1_w(port1_w),
        .port1_data(port1_data),
        .port1_stall(port1_stall),
        .port2_id(port2_id),
        .port2_address(port2_address),
        .port2_req(port2_req),
        .port2_w(port2_w),
        .port2_data(port2_data),
        .port2_stall(port2_stall),
        .tail(tail)
        );

endmodule

graphs/ROB.vcd
$date
	Sun Jan 14 02:19:10 2018
$end
$version
	Icarus Verilog
$end
$timescale
	1s
$end
$scope module test $end
$var wire 1 ! tail $end
$var wire 1 " port2_stall $end
$var wire 1 # port1_stall $end
$var reg 1 $ clk $end
$var reg 5 % port1_address [4:0] $end
$var reg 32 & port1_data [31:0] $end
$var reg 1 ' port1_id $end
$var reg 1 ( port1_req $end
$var reg 1 ) port1_w $end
$var reg 5 * port2_address [4:0] $end
$var reg 32 + port2_data [31:0] $end
$var reg 1 , port2_id $end
$var reg 1 - port2_req $end
$var reg 1 . port2_w $end
$var reg 1 / reset $end
$scope module rob $end
$var wire 1 0 assignment_stall $end
$var wire 1 $ clk $end
$var wire 5 1 current_address [4:0] $end
$var wire 32 2 current_data [31:0] $end
$var wire 1 3 current_write $end
$var wire 5 4 port1_address [4:0] $end
$var wire 32 5 port1_data [31:0] $end
$var wire 1 ' port1_id $end
$var wire 1 ( port1_req $end
$var wire 1 # port1_stall $end
$var wire 1 ) port1_w $end
$var wire 5 6 port2_address [4:0] $end
$var wire 32 7 port2_data [31:0] $end
$var wire 1 , port2_id $end
$var wire 1 - port2_req $end
$var wire 1 " port2_stall $end
$var wire 1 . port2_w $end
$var wire 1 / reset $end
$var wire 1 ! tail $end
$var wire 2 8 we [1:0] $end
$var wire 2 9 valid [1:0] $end
$var wire 1 : selected_port_w $end
$var wire 1 ; selected_port_req $end
$var wire 1 < selected_port_id $end
$var wire 32 = selected_port_data [31:0] $end
$var wire 5 > selected_port_address [4:0] $end
$var wire 1 ? selected_port $end
$var reg 1 @ empty $end
$var reg 1 A head $end
$scope function compare_ids $end
$var reg 1 B compare_ids $end
$var reg 1 C head $end
$var reg 1 D id1 $end
$var reg 1 E id2 $end
$upscope $end
$scope begin genblk1[0] $end
$scope module slot $end
$var wire 1 F erase $end
$var wire 39 G in [38:0] $end
$var wire 39 H out [38:0] $end
$var wire 1 / reset $end
$var wire 1 I stall $end
$var wire 1 $ write $end
$var reg 39 J data [38:0] $end
$upscope $end
$upscope $end
$scope begin genblk1[1] $end
$scope module slot $end
$var wire 1 K erase $end
$var wire 39 L in [38:0] $end
$var wire 39 M out [38:0] $end
$var wire 1 / reset $end
$var wire 1 N stall $end
$var wire 1 $ write $end
$var reg 39 O data [38:0] $end
$upscope $end
$upscope $end
$upscope $end
$upscope $end
$enddefinitions $end
#0
$dumpvars
b0 O
1N
b0 M
bx1 L
0K
b0 J
1I
b0 H
bx1 G
0F
xE
xD
0C
xB
0A
1@
1?
bx >
bx =
x<
0;
x:
b0 9
b0 8
bx 7
bx 6
bx 5
bx 4
03
b0 2
b0 1
00
1/
x.
0-
x,
bx +
bx *
x)
0(
x'
bx &
bx %
0$
0#
0"
z!
$end
#10
1$
#20
0$
0/
#30
1$
#40
0N
b1 =
1<
1:
1;
b10000111 G
b10000111 L
b1 >
0?
0#
1D
0$
b1 &
b1 5
b1 %
b1 4
1(
1)
1'
#50
1$
#51
b10 9
b10 8
b10000111 M
b10000111 O
#60
0$
#70
1$
#80
0I
0<
0:
b10000001 G
b10000001 L
b0 >
1?
1N
0"
0B
0E
1;
0$
b1 +
b1 7
b0 *
b0 6
0.
1-
0,
0(
#90
1$
#91
1F
b11 9
b1 2
b10000001 H
b10000001 J
#100
0$
#110
1B
1C
13
0F
1K
b1 1
1A
x0
0@
1$
#111
b10 9
b0 H
b0 J
#120
1I
0N
1<
1:
b10000111 G
b10000111 L
b1 >
1"
0?
0#
0$
1(
#130
0I
1N
0<
0:
b10000001 G
b10000001 L
b0 >
1#
0"
1?
0B
0C
03
0K
b0 1
b0 2
0A
1$
#131
b0 9
b0 8
b0 M
b0 O
#140
0$
#150
1$
#151
1F
b1 9
b1 2
b10000001 H
b10000001 J
#160
0$
#170
1I
0N
1<
1:
b10000111 G
b10000111 L
b1 >
0#
1"
0?
1B
1C
0F
b0 2
1A
1$
